verification/__init__.py
verification/admin.py
verification/apps.py
verification/forms.py
verification/generators.py
verification/models.py
verification/signals.py
verification/urls.py
verification/views.py
verification/migrations/0001_initial.py
verification/migrations/__init__.py
verification/templates/verification/base.html
verification/templates/verification/claim_form.html
verification/templates/verification/claim_key.html
verification/templates/verification/claim_verify.html
verification/templates/verification/success.html
django_verification-1.4.0.dist-info/WHEEL
django_verification-1.4.0.dist-info/METADATA
django_verification-1.4.0.dist-info/RECORD
